Workbook

Sheet Assumptions
A1: V-Tempe — Financial Model Assumptions (v3, investor-funded marketing)
A2: Edit blue/yellow cells to change the scenario. Marketing spend is modeled as investor capital, tracked separately from the product's own operating economics.
A4: ORGANIC GROWTH (no ad spend)
A5: Month 1 organic installs | B5: 400 | C5: Baseline installs with zero marketing spend — word of mouth, ASO, organic search
A6: Organic month-over-month growth | B6: 0.06 | C6: Pure organic compounding growth
A8: INVESTOR-FUNDED MARKETING
A9: Marketing spend, Month 1 | B9: 500 | C9: Starting monthly ad budget — funded by investor capital, not company operating cash
A10: Marketing spend growth / month | B10: 0.15 | C10: How fast the investor budget scales up. Since it's investor-funded, this can be aggressive without threatening the product's own solvency — see Operating Profit (excl. marketing) below
A11: Cost per paid install (CPI) | B11: 1.5 | C11: Typical mobile fitness-app CPI via Meta/Google UAC is $1-4 depending on region/channel — replace with your real number once you have live campaign data
A13: CONVERSION & RETENTION
A14: Trial-to-paid conversion rate | B14: 0.2 | C14: Share of new installs (organic + paid combined) that convert to a paid subscription
A15: Monthly churn (paying subscribers) | B15: 0.08 | C15: Typical range for consumer mobile subscriptions is 5-10%/month
A17: PRICING
A18: Monthly plan price | B18: 3.99 | C18: Price shown to user, before store commission
A19: Annual plan price | B19: 39 | C19: Equivalent to $3.25/mo if paid annually
A20: Share of subscribers on annual plan | B20: 0.3 | C20: Rest are on the monthly plan
A22: COST OF SERVICE (COGS)
A23: LLM cost per active user / month | B23: 0.85 | C23: OpenRouter (Gemini 2.5 Flash) cost for weekly plan regen + chat; includes buffer for retry waste until backlog item #22 is fixed
A24: One-time LLM cost per new install (onboarding) | B24: 0.07 | C24: First bootstrap generation (training+nutrition+sleep), decomposed calls incl. retries
A25: Server fixed cost / month | B25: 30 | C25: Cloud Run baseline beyond GCP free tier, Secret Manager, logging
A26: Server variable cost / active user / month | B26: 0.01 | C26: Buffer for scale beyond Cloud Run free tier (2M req, 360k GiB-s/mo free)
A28: STORE & TAX
A29: App store commission | B29: 0.15 | C29: 15% under Apple Small Business Program / Google Play first $1M-per-year tier; use 30% for the standard-tier scenario
A30: Corporate tax rate (Armenia) | B30: 0.18 | C30: Standard AM profit tax ~18%. If IT-certification is obtained, this can drop toward 0% — verify current thresholds with a local accountant before relying on this.
A32: CORE OPERATING EXPENSES (self-funded, excl. marketing)
A33: Apple Developer Program (annual, amortized) | B33: 8.25 | C33: $99/year ÷ 12
A34: Google Play (one-time, month 1 only) | B34: 25 | C34: One-time registration fee
A35: Tools & misc / month | B35: 50 | C35: Domain, monitoring, misc SaaS — placeholder, adjust to your actual stack
A36: Founder salary / month | B36: 0 | C36: 0 = pre-revenue solo founder draws nothing; set your real number once you want to pay yourself
A38: Legend: yellow fill = edit these; black = formulas; green = link to another sheet. Green table columns = your own product economics; orange = investor-funded growth spend.

Sheet Monthly Summary
A1: V-Tempe — Audience Growth & Operating Profit by Month
A2: Operating Profit excludes investor-funded marketing spend — it's your own product economics. All figures link live to Monthly Model.
A3: Green cumulative-operating-profit cell = the product has paid back its own Month-1 losses; red = still recovering.
A4: Month | B4: New Installs (organic+paid) | C4: Marketing Spend (investor) | D4: Paying Subscribers | E4: Operating Profit (excl. marketing) | F4: Cumulative Operating Profit | G4: Cumulative Investor Spend
A5: ='Monthly Model'!A3 | B5: ='Monthly Model'!E3 | C5: ='Monthly Model'!C3 | D5: ='Monthly Model'!J3 | E5: ='Monthly Model'!U3 | F5: ='Monthly Model'!V3 | G5: ='Monthly Model'!W3
A6: ='Monthly Model'!A4 | B6: ='Monthly Model'!E4 | C6: ='Monthly Model'!C4 | D6: ='Monthly Model'!J4 | E6: ='Monthly Model'!U4 | F6: ='Monthly Model'!V4 | G6: ='Monthly Model'!W4
A7: ='Monthly Model'!A5 | B7: ='Monthly Model'!E5 | C7: ='Monthly Model'!C5 | D7: ='Monthly Model'!J5 | E7: ='Monthly Model'!U5 | F7: ='Monthly Model'!V5 | G7: ='Monthly Model'!W5
A8: ='Monthly Model'!A6 | B8: ='Monthly Model'!E6 | C8: ='Monthly Model'!C6 | D8: ='Monthly Model'!J6 | E8: ='Monthly Model'!U6 | F8: ='Monthly Model'!V6 | G8: ='Monthly Model'!W6
A9: ='Monthly Model'!A7 | B9: ='Monthly Model'!E7 | C9: ='Monthly Model'!C7 | D9: ='Monthly Model'!J7 | E9: ='Monthly Model'!U7 | F9: ='Monthly Model'!V7 | G9: ='Monthly Model'!W7
A10: ='Monthly Model'!A8 | B10: ='Monthly Model'!E8 | C10: ='Monthly Model'!C8 | D10: ='Monthly Model'!J8 | E10: ='Monthly Model'!U8 | F10: ='Monthly Model'!V8 | G10: ='Monthly Model'!W8
A11: ='Monthly Model'!A9 | B11: ='Monthly Model'!E9 | C11: ='Monthly Model'!C9 | D11: ='Monthly Model'!J9 | E11: ='Monthly Model'!U9 | F11: ='Monthly Model'!V9 | G11: ='Monthly Model'!W9
A12: ='Monthly Model'!A10 | B12: ='Monthly Model'!E10 | C12: ='Monthly Model'!C10 | D12: ='Monthly Model'!J10 | E12: ='Monthly Model'!U10 | F12: ='Monthly Model'!V10 | G12: ='Monthly Model'!W10
A13: ='Monthly Model'!A11 | B13: ='Monthly Model'!E11 | C13: ='Monthly Model'!C11 | D13: ='Monthly Model'!J11 | E13: ='Monthly Model'!U11 | F13: ='Monthly Model'!V11 | G13: ='Monthly Model'!W11
A14: ='Monthly Model'!A12 | B14: ='Monthly Model'!E12 | C14: ='Monthly Model'!C12 | D14: ='Monthly Model'!J12 | E14: ='Monthly Model'!U12 | F14: ='Monthly Model'!V12 | G14: ='Monthly Model'!W12
A15: ='Monthly Model'!A13 | B15: ='Monthly Model'!E13 | C15: ='Monthly Model'!C13 | D15: ='Monthly Model'!J13 | E15: ='Monthly Model'!U13 | F15: ='Monthly Model'!V13 | G15: ='Monthly Model'!W13
A16: ='Monthly Model'!A14 | B16: ='Monthly Model'!E14 | C16: ='Monthly Model'!C14 | D16: ='Monthly Model'!J14 | E16: ='Monthly Model'!U14 | F16: ='Monthly Model'!V14 | G16: ='Monthly Model'!W14
A18: YEAR 1 | B18: =SUM(B5:B16) | C18: =SUM(C5:C16) | E18: =SUM(E5:E16) | F18: =F16 | G18: =G16

Sheet Monthly Model
A1: V-Tempe — 12-Month Financial Model (v3): Operating Profit vs Investor-Funded Growth
A2: Month | B2: Organic Installs | C2: Marketing Spend (investor) | D2: Paid Installs | E2: New Installs (Total) | F2: Active Users (cost base) | G2: Paying Subs (begin) | H2: New Conversions | I2: Churned Subs | J2: Paying Subs (end) | K2: Gross Revenue | L2: Store Commission | M2: Net Revenue | N2: LLM Cost | O2: Server Cost | P2: Total COGS | Q2: Gross Profit | R2: Core OpEx (self-funded) | S2: Operating Pretax (excl. marketing) | T2: Operating Tax | U2: Operating Profit (excl. marketing) | V2: Cumulative Operating Profit | W2: Cumulative Marketing Spend (investor capital deployed)
A3: 1 | B3: =Assumptions!$B$5 | C3: =Assumptions!$B$9 | D3: =C3/Assumptions!$B$11 | E3: =B3+D3 | F3: =E3+G3 | G3: 0 | H3: =E3*Assumptions!$B$14 | I3: =G3*Assumptions!$B$15 | J3: =G3+H3-I3 | K3: =AVERAGE(G3,J3)*(Assumptions!$B$18*(1-Assumptions!$B$20)+(Assumptions!$B$19/12)*Assumptions!$B$20) | L3: =K3*Assumptions!$B$29 | M3: =K3-L3 | N3: =F3*Assumptions!$B$23+E3*Assumptions!$B$24 | O3: =Assumptions!$B$25+F3*Assumptions!$B$26 | P3: =N3+O3 | Q3: =M3-P3 | R3: =Assumptions!$B$33+Assumptions!$B$35+Assumptions!$B$36+Assumptions!$B$34 | S3: =Q3-R3 | T3: =MAX(0,S3)*Assumptions!$B$30 | U3: =S3-T3 | V3: =U3 | W3: =C3
A4: 2 | B4: =B3*(1+Assumptions!$B$6) | C4: =C3*(1+Assumptions!$B$10) | D4: =C4/Assumptions!$B$11 | E4: =B4+D4 | F4: =E4+G4 | G4: =J3 | H4: =E4*Assumptions!$B$14 | I4: =G4*Assumptions!$B$15 | J4: =G4+H4-I4 | K4: =AVERAGE(G4,J4)*(Assumptions!$B$18*(1-Assumptions!$B$20)+(Assumptions!$B$19/12)*Assumptions!$B$20) | L4: =K4*Assumptions!$B$29 | M4: =K4-L4 | N4: =F4*Assumptions!$B$23+E4*Assumptions!$B$24 | O4: =Assumptions!$B$25+F4*Assumptions!$B$26 | P4: =N4+O4 | Q4: =M4-P4 | R4: =Assumptions!$B$33+Assumptions!$B$35+Assumptions!$B$36 | S4: =Q4-R4 | T4: =MAX(0,S4)*Assumptions!$B$30 | U4: =S4-T4 | V4: =V3+U4 | W4: =W3+C4
A5: 3 | B5: =B4*(1+Assumptions!$B$6) | C5: =C4*(1+Assumptions!$B$10) | D5: =C5/Assumptions!$B$11 | E5: =B5+D5 | F5: =E5+G5 | G5: =J4 | H5: =E5*Assumptions!$B$14 | I5: =G5*Assumptions!$B$15 | J5: =G5+H5-I5 | K5: =AVERAGE(G5,J5)*(Assumptions!$B$18*(1-Assumptions!$B$20)+(Assumptions!$B$19/12)*Assumptions!$B$20) | L5: =K5*Assumptions!$B$29 | M5: =K5-L5 | N5: =F5*Assumptions!$B$23+E5*Assumptions!$B$24 | O5: =Assumptions!$B$25+F5*Assumptions!$B$26 | P5: =N5+O5 | Q5: =M5-P5 | R5: =Assumptions!$B$33+Assumptions!$B$35+Assumptions!$B$36 | S5: =Q5-R5 | T5: =MAX(0,S5)*Assumptions!$B$30 | U5: =S5-T5 | V5: =V4+U5 | W5: =W4+C5
A6: 4 | B6: =B5*(1+Assumptions!$B$6) | C6: =C5*(1+Assumptions!$B$10) | D6: =C6/Assumptions!$B$11 | E6: =B6+D6 | F6: =E6+G6 | G6: =J5 | H6: =E6*Assumptions!$B$14 | I6: =G6*Assumptions!$B$15 | J6: =G6+H6-I6 | K6: =AVERAGE(G6,J6)*(Assumptions!$B$18*(1-Assumptions!$B$20)+(Assumptions!$B$19/12)*Assumptions!$B$20) | L6: =K6*Assumptions!$B$29 | M6: =K6-L6 | N6: =F6*Assumptions!$B$23+E6*Assumptions!$B$24 | O6: =Assumptions!$B$25+F6*Assumptions!$B$26 | P6: =N6+O6 | Q6: =M6-P6 | R6: =Assumptions!$B$33+Assumptions!$B$35+Assumptions!$B$36 | S6: =Q6-R6 | T6: =MAX(0,S6)*Assumptions!$B$30 | U6: =S6-T6 | V6: =V5+U6 | W6: =W5+C6
A7: 5 | B7: =B6*(1+Assumptions!$B$6) | C7: =C6*(1+Assumptions!$B$10) | D7: =C7/Assumptions!$B$11 | E7: =B7+D7 | F7: =E7+G7 | G7: =J6 | H7: =E7*Assumptions!$B$14 | I7: =G7*Assumptions!$B$15 | J7: =G7+H7-I7 | K7: =AVERAGE(G7,J7)*(Assumptions!$B$18*(1-Assumptions!$B$20)+(Assumptions!$B$19/12)*Assumptions!$B$20) | L7: =K7*Assumptions!$B$29 | M7: =K7-L7 | N7: =F7*Assumptions!$B$23+E7*Assumptions!$B$24 | O7: =Assumptions!$B$25+F7*Assumptions!$B$26 | P7: =N7+O7 | Q7: =M7-P7 | R7: =Assumptions!$B$33+Assumptions!$B$35+Assumptions!$B$36 | S7: =Q7-R7 | T7: =MAX(0,S7)*Assumptions!$B$30 | U7: =S7-T7 | V7: =V6+U7 | W7: =W6+C7
A8: 6 | B8: =B7*(1+Assumptions!$B$6) | C8: =C7*(1+Assumptions!$B$10) | D8: =C8/Assumptions!$B$11 | E8: =B8+D8 | F8: =E8+G8 | G8: =J7 | H8: =E8*Assumptions!$B$14 | I8: =G8*Assumptions!$B$15 | J8: =G8+H8-I8 | K8: =AVERAGE(G8,J8)*(Assumptions!$B$18*(1-Assumptions!$B$20)+(Assumptions!$B$19/12)*Assumptions!$B$20) | L8: =K8*Assumptions!$B$29 | M8: =K8-L8 | N8: =F8*Assumptions!$B$23+E8*Assumptions!$B$24 | O8: =Assumptions!$B$25+F8*Assumptions!$B$26 | P8: =N8+O8 | Q8: =M8-P8 | R8: =Assumptions!$B$33+Assumptions!$B$35+Assumptions!$B$36 | S8: =Q8-R8 | T8: =MAX(0,S8)*Assumptions!$B$30 | U8: =S8-T8 | V8: =V7+U8 | W8: =W7+C8
A9: 7 | B9: =B8*(1+Assumptions!$B$6) | C9: =C8*(1+Assumptions!$B$10) | D9: =C9/Assumptions!$B$11 | E9: =B9+D9 | F9: =E9+G9 | G9: =J8 | H9: =E9*Assumptions!$B$14 | I9: =G9*Assumptions!$B$15 | J9: =G9+H9-I9 | K9: =AVERAGE(G9,J9)*(Assumptions!$B$18*(1-Assumptions!$B$20)+(Assumptions!$B$19/12)*Assumptions!$B$20) | L9: =K9*Assumptions!$B$29 | M9: =K9-L9 | N9: =F9*Assumptions!$B$23+E9*Assumptions!$B$24 | O9: =Assumptions!$B$25+F9*Assumptions!$B$26 | P9: =N9+O9 | Q9: =M9-P9 | R9: =Assumptions!$B$33+Assumptions!$B$35+Assumptions!$B$36 | S9: =Q9-R9 | T9: =MAX(0,S9)*Assumptions!$B$30 | U9: =S9-T9 | V9: =V8+U9 | W9: =W8+C9
A10: 8 | B10: =B9*(1+Assumptions!$B$6) | C10: =C9*(1+Assumptions!$B$10) | D10: =C10/Assumptions!$B$11 | E10: =B10+D10 | F10: =E10+G10 | G10: =J9 | H10: =E10*Assumptions!$B$14 | I10: =G10*Assumptions!$B$15 | J10: =G10+H10-I10 | K10: =AVERAGE(G10,J10)*(Assumptions!$B$18*(1-Assumptions!$B$20)+(Assumptions!$B$19/12)*Assumptions!$B$20) | L10: =K10*Assumptions!$B$29 | M10: =K10-L10 | N10: =F10*Assumptions!$B$23+E10*Assumptions!$B$24 | O10: =Assumptions!$B$25+F10*Assumptions!$B$26 | P10: =N10+O10 | Q10: =M10-P10 | R10: =Assumptions!$B$33+Assumptions!$B$35+Assumptions!$B$36 | S10: =Q10-R10 | T10: =MAX(0,S10)*Assumptions!$B$30 | U10: =S10-T10 | V10: =V9+U10 | W10: =W9+C10
A11: 9 | B11: =B10*(1+Assumptions!$B$6) | C11: =C10*(1+Assumptions!$B$10) | D11: =C11/Assumptions!$B$11 | E11: =B11+D11 | F11: =E11+G11 | G11: =J10 | H11: =E11*Assumptions!$B$14 | I11: =G11*Assumptions!$B$15 | J11: =G11+H11-I11 | K11: =AVERAGE(G11,J11)*(Assumptions!$B$18*(1-Assumptions!$B$20)+(Assumptions!$B$19/12)*Assumptions!$B$20) | L11: =K11*Assumptions!$B$29 | M11: =K11-L11 | N11: =F11*Assumptions!$B$23+E11*Assumptions!$B$24 | O11: =Assumptions!$B$25+F11*Assumptions!$B$26 | P11: =N11+O11 | Q11: =M11-P11 | R11: =Assumptions!$B$33+Assumptions!$B$35+Assumptions!$B$36 | S11: =Q11-R11 | T11: =MAX(0,S11)*Assumptions!$B$30 | U11: =S11-T11 | V11: =V10+U11 | W11: =W10+C11
A12: 10 | B12: =B11*(1+Assumptions!$B$6) | C12: =C11*(1+Assumptions!$B$10) | D12: =C12/Assumptions!$B$11 | E12: =B12+D12 | F12: =E12+G12 | G12: =J11 | H12: =E12*Assumptions!$B$14 | I12: =G12*Assumptions!$B$15 | J12: =G12+H12-I12 | K12: =AVERAGE(G12,J12)*(Assumptions!$B$18*(1-Assumptions!$B$20)+(Assumptions!$B$19/12)*Assumptions!$B$20) | L12: =K12*Assumptions!$B$29 | M12: =K12-L12 | N12: =F12*Assumptions!$B$23+E12*Assumptions!$B$24 | O12: =Assumptions!$B$25+F12*Assumptions!$B$26 | P12: =N12+O12 | Q12: =M12-P12 | R12: =Assumptions!$B$33+Assumptions!$B$35+Assumptions!$B$36 | S12: =Q12-R12 | T12: =MAX(0,S12)*Assumptions!$B$30 | U12: =S12-T12 | V12: =V11+U12 | W12: =W11+C12
A13: 11 | B13: =B12*(1+Assumptions!$B$6) | C13: =C12*(1+Assumptions!$B$10) | D13: =C13/Assumptions!$B$11 | E13: =B13+D13 | F13: =E13+G13 | G13: =J12 | H13: =E13*Assumptions!$B$14 | I13: =G13*Assumptions!$B$15 | J13: =G13+H13-I13 | K13: =AVERAGE(G13,J13)*(Assumptions!$B$18*(1-Assumptions!$B$20)+(Assumptions!$B$19/12)*Assumptions!$B$20) | L13: =K13*Assumptions!$B$29 | M13: =K13-L13 | N13: =F13*Assumptions!$B$23+E13*Assumptions!$B$24 | O13: =Assumptions!$B$25+F13*Assumptions!$B$26 | P13: =N13+O13 | Q13: =M13-P13 | R13: =Assumptions!$B$33+Assumptions!$B$35+Assumptions!$B$36 | S13: =Q13-R13 | T13: =MAX(0,S13)*Assumptions!$B$30 | U13: =S13-T13 | V13: =V12+U13 | W13: =W12+C13
A14: 12 | B14: =B13*(1+Assumptions!$B$6) | C14: =C13*(1+Assumptions!$B$10) | D14: =C14/Assumptions!$B$11 | E14: =B14+D14 | F14: =E14+G14 | G14: =J13 | H14: =E14*Assumptions!$B$14 | I14: =G14*Assumptions!$B$15 | J14: =G14+H14-I14 | K14: =AVERAGE(G14,J14)*(Assumptions!$B$18*(1-Assumptions!$B$20)+(Assumptions!$B$19/12)*Assumptions!$B$20) | L14: =K14*Assumptions!$B$29 | M14: =K14-L14 | N14: =F14*Assumptions!$B$23+E14*Assumptions!$B$24 | O14: =Assumptions!$B$25+F14*Assumptions!$B$26 | P14: =N14+O14 | Q14: =M14-P14 | R14: =Assumptions!$B$33+Assumptions!$B$35+Assumptions!$B$36 | S14: =Q14-R14 | T14: =MAX(0,S14)*Assumptions!$B$30 | U14: =S14-T14 | V14: =V13+U14 | W14: =W13+C14
A16: YEAR 1 TOTAL | B16: =SUM(B3:B14) | C16: =SUM(C3:C14) | D16: =SUM(D3:D14) | E16: =SUM(E3:E14) | K16: =SUM(K3:K14) | L16: =SUM(L3:L14) | M16: =SUM(M3:M14) | N16: =SUM(N3:N14) | O16: =SUM(O3:O14) | P16: =SUM(P3:P14) | Q16: =SUM(Q3:Q14) | R16: =SUM(R3:R14) | ... U16: =SUM(U3:U14) | V16: =V14 | W16: =W14

Sheet Summary
A1: V-Tempe — Year 1 Summary (v3): Operating Profit vs Investor-Funded Growth
A3: REVENUE & AUDIENCE
A4: Total new installs (Year 1) | B4: ='Monthly Model'!E16
A5: of which paid (investor-marketing-driven) | B5: ='Monthly Model'!D16
A6: Paying subscribers (Month 12, ending) | B6: ='Monthly Model'!J14
A7: Exit ARR (annualized, Month 12) | B7: ='Monthly Model'!K14*12
A8: Year 1 gross revenue | B8: ='Monthly Model'!K16
A10: YOUR OWN ECONOMICS — OPERATING PROFIT (excl. investor marketing)
A11: Year 1 operating profit (self-funded, excl. marketing) | B11: ='Monthly Model'!V14
A12: First month operating profit turns positive | B12: =IFERROR(INDEX('Monthly Model'!A3:A14,MATCH(TRUE(),INDEX('Monthly Model'!U3:U14>0,0),0)),"not within 12 months") | C12: First month with a positive Operating Profit for that single month
A13: First month cumulative operating profit turns positive | B13: =IFERROR(INDEX('Monthly Model'!A3:A14,MATCH(TRUE(),INDEX('Monthly Model'!V3:V14>0,0),0)),"not within 12 months") | C13: The product pays back its own Month-1 losses by this month — regardless of how aggressive the investor-funded marketing spend is
A15: INVESTOR MARKETING — CAPITAL DEPLOYED & RETURN
A16: Year 1 total marketing spend (investor capital deployed) | B16: ='Monthly Model'!W14
A17: Blended CAC (CPI / conversion rate) | B17: =Assumptions!$B$11/Assumptions!$B$14 | C17: Cost to acquire one paying subscriber via paid marketing
A18: Gross profit per subscriber / month | B18: =(((Assumptions!$B$18*(1-Assumptions!$B$20)+(Assumptions!$B$19/12)*Assumptions!$B$20)*(1-Assumptions!$B$29))-(Assumptions!$B$23+Assumptions!$B$26)) | C18: Net revenue per subscriber (after store commission) minus variable COGS — the margin that pays back CAC
A19: CAC payback period (months) | B19: =B17/B18 | C19: Months of subscriber margin needed to recover the acquisition cost. Under 12 months is healthy for consumer subscription; under 6 is excellent.
A20: Contribution-margin LTV per subscriber | B20: =(((Assumptions!$B$18*(1-Assumptions!$B$20)+(Assumptions!$B$19/12)*Assumptions!$B$20)*(1-Assumptions!$B$29))-(Assumptions!$B$23+Assumptions!$B$26))/Assumptions!$B$15 | C20: Gross-profit-per-month ÷ churn rate — the conservative LTV investors actually look at (nets out COGS, not just revenue)
A21: LTV : CAC ratio | B21: =B20/B17 | C21: Healthy SaaS/subscription benchmark is ≥3x. This is what justifies scaling the investor marketing budget.
A23: Reading this model: the product is expected to be self-sustaining on its own (green columns in Monthly Model) well within Year 1,
A24: independent of how aggressively the investor marketing budget (orange columns) scales — that spend is evaluated on CAC payback and LTV:CAC, not on whether it fits inside the product's own cash flow.
A25: If CAC payback lengthens or LTV:CAC drops below ~3x as you scale spend (diminishing returns on ad channels), pull back — that's the signal, not the P&L line alone.
