Workbook

Sheet Assumptions
A1: V-Tempe — Financial Model Assumptions
A2: Edit blue cells (yellow fill) to change the scenario. All other sheets recalculate automatically.
A4: GROWTH & CONVERSION
A5: Month 1 new installs | B5: 500 | C5: Starting monthly new-install volume (organic/ASO, no paid marketing assumed)
A6: Month-over-month install growth | B6: 0.12 | C6: Organic growth rate of new installs, compounding monthly
A7: Trial-to-paid conversion rate | B7: 0.2 | C7: Share of new installs that convert to a paid subscription (assumes free trial, no perma-free tier)
A8: Monthly churn (paying subscribers) | B8: 0.08 | C8: Typical range for consumer mobile subscriptions is 5-10%/month
A10: PRICING
A11: Monthly plan price | B11: 3.99 | C11: Price shown to user, before store commission
A12: Annual plan price | B12: 39 | C12: Equivalent to $3.25/mo if paid annually
A13: Share of subscribers on annual plan | B13: 0.3 | C13: Rest are on the monthly plan
A15: COST OF SERVICE (COGS)
A16: LLM cost per active user / month | B16: 0.85 | C16: OpenRouter (Gemini 2.5 Flash) cost for weekly plan regen + chat; includes buffer for retry waste until backlog item #22 is fixed
A17: One-time LLM cost per new install (onboarding) | B17: 0.07 | C17: First bootstrap generation (training+nutrition+sleep), decomposed calls incl. retries
A18: Server fixed cost / month | B18: 30 | C18: Cloud Run baseline beyond GCP free tier, Secret Manager, logging
A19: Server variable cost / active user / month | B19: 0.01 | C19: Buffer for scale beyond Cloud Run free tier (2M req, 360k GiB-s/mo free)
A21: STORE & TAX
A22: App store commission | B22: 0.15 | C22: 15% under Apple Small Business Program / Google Play first $1M-per-year tier; use 30% for the standard-tier scenario
A23: Corporate tax rate (Armenia) | B23: 0.18 | C23: Standard AM profit tax ~18%. If IT-certification is obtained, this can drop toward 0% — verify current thresholds with a local accountant before relying on this.
A25: FIXED OPERATING EXPENSES (non-COGS)
A26: Apple Developer Program (annual, amortized) | B26: 8.25 | C26: $99/year ÷ 12
A27: Google Play (one-time, month 1 only) | B27: 25 | C27: One-time registration fee
A28: Tools & misc / month | B28: 50 | C28: Domain, monitoring, misc SaaS — placeholder, adjust to your actual stack
A29: Founder salary / month | B29: 0 | C29: 0 = pre-revenue solo founder draws nothing; set your real number once you want to pay yourself
A30: Marketing spend / month | B30: 0 | C30: 0 = organic growth only; set a budget to model paid acquisition (also raises Month-1 installs / growth rate above if used)
A32: Legend: yellow fill = edit these; black = formulas; green = link to another sheet.

Sheet Monthly Model
A1: V-Tempe — 12-Month Financial Model
A2: Month | B2: New Installs | C2: Active Users (cost base) | D2: Paying Subs (begin) | E2: New Conversions | F2: Churned Subs | G2: Paying Subs (end) | H2: Gross Revenue | I2: Store Commission | J2: Net Revenue | K2: LLM Cost | L2: Server Cost | M2: Total COGS | N2: Gross Profit | O2: OpEx | P2: Pretax Profit | Q2: Tax | R2: Net Profit | S2: Cumulative Net Profit
A3: 1 | B3: =Assumptions!$B$5 -> 500 | C3: =B3+D3 -> 500 | D3: 0 | E3: =B3*Assumptions!$B$7 -> 100 | F3: =D3*Assumptions!$B$8 -> 0 | G3: =D3+E3-F3 -> 100 | H3: =AVERAGE(D3,G3)*(Assumptions!$B$11*(1-Assumptions!$B$13)+(Assumptions!$B$12/12)*Assumptions!$B$13) -> 188.4 | I3: =H3*Assumptions!$B$22 -> 28.26 | J3: =H3-I3 -> 160.14 | K3: =C3*Assumptions!$B$16+B3*Assumptions!$B$17 -> 460 | L3: =Assumptions!$B$18+C3*Assumptions!$B$19 -> 35 | M3: =K3+L3 -> 495 | N3: =J3-M3 -> -334.86 | O3: =Assumptions!$B$26+Assumptions!$B$28+Assumptions!$B$29+Assumptions!$B$30+Assumptions!$B$27 -> 83.25 | P3: =N3-O3 -> -418.11 | Q3: =MAX(0,P3)*Assumptions!$B$23 -> 0 | R3: =P3-Q3 -> -418.11 | S3: =R3 -> -418.11
A4: 2 | B4: =B3*(1+Assumptions!$B$6) -> 560 | C4: =B4+D4 -> 660 | D4: =G3 -> 100 | E4: =B4*Assumptions!$B$7 -> 112 | F4: =D4*Assumptions!$B$8 -> 8 | G4: =D4+E4-F4 -> 204 | H4: =AVERAGE(D4,G4)*(Assumptions!$B$11*(1-Assumptions!$B$13)+(Assumptions!$B$12/12)*Assumptions!$B$13) -> 572.736 | I4: =H4*Assumptions!$B$22 -> 85.9104 | J4: =H4-I4 -> 486.8256 | K4: =C4*Assumptions!$B$16+B4*Assumptions!$B$17 -> 600.2 | L4: =Assumptions!$B$18+C4*Assumptions!$B$19 -> 36.6 | M4: =K4+L4 -> 636.8 | N4: =J4-M4 -> -149.9744 | O4: =Assumptions!$B$26+Assumptions!$B$28+Assumptions!$B$29+Assumptions!$B$30 -> 58.25 | P4: =N4-O4 -> -208.2244 | Q4: =MAX(0,P4)*Assumptions!$B$23 -> 0 | R4: =P4-Q4 -> -208.2244 | S4: =S3+R4 -> -626.3344
A5: 3 | B5: =B4*(1+Assumptions!$B$6) -> 627.2 | C5: =B5+D5 -> 831.2 | D5: =G4 -> 204 | E5: =B5*Assumptions!$B$7 -> 125.44 | F5: =D5*Assumptions!$B$8 -> 16.32 | G5: =D5+E5-F5 -> 313.12 | H5: =AVERAGE(D5,G5)*(Assumptions!$B$11*(1-Assumptions!$B$13)+(Assumptions!$B$12/12)*Assumptions!$B$13) -> 974.25408 | I5: =H5*Assumptions!$B$22 -> 146.13811 | J5: =H5-I5 -> 828.11597 | K5: =C5*Assumptions!$B$16+B5*Assumptions!$B$17 -> 750.424 | L5: =Assumptions!$B$18+C5*Assumptions!$B$19 -> 38.312 | M5: =K5+L5 -> 788.736 | N5: =J5-M5 -> 39.379968 | O5: =Assumptions!$B$26+Assumptions!$B$28+Assumptions!$B$29+Assumptions!$B$30 -> 58.25 | P5: =N5-O5 -> -18.870032 | Q5: =MAX(0,P5)*Assumptions!$B$23 -> 0 | R5: =P5-Q5 -> -18.870032 | S5: =S4+R5 -> -645.20443
A6: 4 | B6: =B5*(1+Assumptions!$B$6) -> 702.464 | C6: =B6+D6 -> 1015.584 | D6: =G5 -> 313.12 | E6: =B6*Assumptions!$B$7 -> 140.4928 | F6: =D6*Assumptions!$B$8 -> 25.0496 | G6: =D6+E6-F6 -> 428.5632 | H6: =AVERAGE(D6,G6)*(Assumptions!$B$11*(1-Assumptions!$B$13)+(Assumptions!$B$12/12)*Assumptions!$B$13) -> 1397.3311 | I6: =H6*Assumptions!$B$22 -> 209.59967 | J6: =H6-I6 -> 1187.7315 | K6: =C6*Assumptions!$B$16+B6*Assumptions!$B$17 -> 912.41888 | L6: =Assumptions!$B$18+C6*Assumptions!$B$19 -> 40.15584 | M6: =K6+L6 -> 952.57472 | N6: =J6-M6 -> 235.15676 | O6: =Assumptions!$B$26+Assumptions!$B$28+Assumptions!$B$29+Assumptions!$B$30 -> 58.25 | P6: =N6-O6 -> 176.90676 | Q6: =MAX(0,P6)*Assumptions!$B$23 -> 31.843216 | R6: =P6-Q6 -> 145.06354 | S6: =S5+R6 -> -500.14089
A7: 5 | B7: =B6*(1+Assumptions!$B$6) -> 786.75968 | C7: =B7+D7 -> 1215.3229 | D7: =G6 -> 428.5632 | E7: =B7*Assumptions!$B$7 -> 157.35194 | F7: =D7*Assumptions!$B$8 -> 34.285056 | G7: =D7+E7-F7 -> 551.63008 | H7: =AVERAGE(D7,G7)*(Assumptions!$B$11*(1-Assumptions!$B$13)+(Assumptions!$B$12/12)*Assumptions!$B$13) -> 1846.6841 | I7: =H7*Assumptions!$B$22 -> 277.00262 | J7: =H7-I7 -> 1569.6815 | K7: =C7*Assumptions!$B$16+B7*Assumptions!$B$17 -> 1088.0976 | L7: =Assumptions!$B$18+C7*Assumptions!$B$19 -> 42.153229 | M7: =K7+L7 -> 1130.2509 | N7: =J7-M7 -> 439.43066 | O7: =Assumptions!$B$26+Assumptions!$B$28+Assumptions!$B$29+Assumptions!$B$30 -> 58.25 | P7: =N7-O7 -> 381.18066 | Q7: =MAX(0,P7)*Assumptions!$B$23 -> 68.61252 | R7: =P7-Q7 -> 312.56814 | S7: =S6+R7 -> -187.57275
A8: 6 | B8: =B7*(1+Assumptions!$B$6) -> 881.17084 | C8: =B8+D8 -> 1432.8009 | D8: =G7 -> 551.63008 | E8: =B8*Assumptions!$B$7 -> 176.23417 | F8: =D8*Assumptions!$B$8 -> 44.130406 | G8: =D8+E8-F8 -> 683.73384 | H8: =AVERAGE(D8,G8)*(Assumptions!$B$11*(1-Assumptions!$B$13)+(Assumptions!$B$12/12)*Assumptions!$B$13) -> 2327.4256 | I8: =H8*Assumptions!$B$22 -> 349.11384 | J8: =H8-I8 -> 1978.3118 | K8: =C8*Assumptions!$B$16+B8*Assumptions!$B$17 -> 1279.5627 | L8: =Assumptions!$B$18+C8*Assumptions!$B$19 -> 44.328009 | M8: =K8+L8 -> 1323.8908 | N8: =J8-M8 -> 654.42103 | O8: =Assumptions!$B$26+Assumptions!$B$28+Assumptions!$B$29+Assumptions!$B$30 -> 58.25 | P8: =N8-O8 -> 596.17103 | Q8: =MAX(0,P8)*Assumptions!$B$23 -> 107.31079 | R8: =P8-Q8 -> 488.86025 | S8: =S7+R8 -> 301.2875
A9: 7 | B9: =B8*(1+Assumptions!$B$6) -> 986.91134 | C9: =B9+D9 -> 1670.6452 | D9: =G8 -> 683.73384 | E9: =B9*Assumptions!$B$7 -> 197.38227 | F9: =D9*Assumptions!$B$8 -> 54.698707 | G9: =D9+E9-F9 -> 826.4174 | H9: =AVERAGE(D9,G9)*(Assumptions!$B$11*(1-Assumptions!$B$13)+(Assumptions!$B$12/12)*Assumptions!$B$13) -> 2845.1249 | I9: =H9*Assumptions!$B$22 -> 426.76874 | J9: =H9-I9 -> 2418.3562 | K9: =C9*Assumptions!$B$16+B9*Assumptions!$B$17 -> 1489.1322 | L9: =Assumptions!$B$18+C9*Assumptions!$B$19 -> 46.706452 | M9: =K9+L9 -> 1535.8387 | N9: =J9-M9 -> 882.51755 | O9: =Assumptions!$B$26+Assumptions!$B$28+Assumptions!$B$29+Assumptions!$B$30 -> 58.25 | P9: =N9-O9 -> 824.26755 | Q9: =MAX(0,P9)*Assumptions!$B$23 -> 148.36816 | R9: =P9-Q9 -> 675.89939 | S9: =S8+R9 -> 977.18689
A10: 8 | B10: =B9*(1+Assumptions!$B$6) -> 1105.3407 | C10: =B10+D10 -> 1931.7581 | D10: =G9 -> 826.4174 | E10: =B10*Assumptions!$B$7 -> 221.06814 | F10: =D10*Assumptions!$B$8 -> 66.113392 | G10: =D10+E10-F10 -> 981.37215 | H10: =AVERAGE(D10,G10)*(Assumptions!$B$11*(1-Assumptions!$B$13)+(Assumptions!$B$12/12)*Assumptions!$B$13) -> 3405.8755 | I10: =H10*Assumptions!$B$22 -> 510.88133 | J10: =H10-I10 -> 2894.9942 | K10: =C10*Assumptions!$B$16+B10*Assumptions!$B$17 -> 1719.3682 | L10: =Assumptions!$B$18+C10*Assumptions!$B$19 -> 49.317581 | M10: =K10+L10 -> 1768.6858 | N10: =J10-M10 -> 1126.3084 | O10: =Assumptions!$B$26+Assumptions!$B$28+Assumptions!$B$29+Assumptions!$B$30 -> 58.25 | P10: =N10-O10 -> 1068.0584 | Q10: =MAX(0,P10)*Assumptions!$B$23 -> 192.25051 | R10: =P10-Q10 -> 875.80786 | S10: =S9+R10 -> 1852.9948
A11: 9 | B11: =B10*(1+Assumptions!$B$6) -> 1237.9816 | C11: =B11+D11 -> 2219.3537 | D11: =G10 -> 981.37215 | E11: =B11*Assumptions!$B$7 -> 247.59632 | F11: =D11*Assumptions!$B$8 -> 78.509772 | G11: =D11+E11-F11 -> 1150.4587 | H11: =AVERAGE(D11,G11)*(Assumptions!$B$11*(1-Assumptions!$B$13)+(Assumptions!$B$12/12)*Assumptions!$B$13) -> 4016.3693 | I11: =H11*Assumptions!$B$22 -> 602.4554 | J11: =H11-I11 -> 3413.9139 | K11: =C11*Assumptions!$B$16+B11*Assumptions!$B$17 -> 1973.1094 | L11: =Assumptions!$B$18+C11*Assumptions!$B$19 -> 52.193537 | M11: =K11+L11 -> 2025.3029 | N11: =J11-M11 -> 1388.611 | O11: =Assumptions!$B$26+Assumptions!$B$28+Assumptions!$B$29+Assumptions!$B$30 -> 58.25 | P11: =N11-O11 -> 1330.361 | Q11: =MAX(0,P11)*Assumptions!$B$23 -> 239.46498 | R11: =P11-Q11 -> 1090.896 | S11: =S10+R11 -> 2943.8908
A12: 10 | B12: =B11*(1+Assumptions!$B$6) -> 1386.5394 | C12: =B12+D12 -> 2536.9981 | D12: =G11 -> 1150.4587 | E12: =B12*Assumptions!$B$7 -> 277.30788 | F12: =D12*Assumptions!$B$8 -> 92.036696 | G12: =D12+E12-F12 -> 1335.7299 | H12: =AVERAGE(D12,G12)*(Assumptions!$B$11*(1-Assumptions!$B$13)+(Assumptions!$B$12/12)*Assumptions!$B$13) -> 4683.9793 | I12: =H12*Assumptions!$B$22 -> 702.59689 | J12: =H12-I12 -> 3981.3824 | K12: =C12*Assumptions!$B$16+B12*Assumptions!$B$17 -> 2253.5061 | L12: =Assumptions!$B$18+C12*Assumptions!$B$19 -> 55.369981 | M12: =K12+L12 -> 2308.8761 | N12: =J12-M12 -> 1672.5063 | O12: =Assumptions!$B$26+Assumptions!$B$28+Assumptions!$B$29+Assumptions!$B$30 -> 58.25 | P12: =N12-O12 -> 1614.2563 | Q12: =MAX(0,P12)*Assumptions!$B$23 -> 290.56613 | R12: =P12-Q12 -> 1323.6902 | S12: =S11+R12 -> 4267.5809
A13: 11 | B13: =B12*(1+Assumptions!$B$6) -> 1552.9241 | C13: =B13+D13 -> 2888.654 | D13: =G12 -> 1335.7299 | E13: =B13*Assumptions!$B$7 -> 310.58482 | F13: =D13*Assumptions!$B$8 -> 106.85839 | G13: =D13+E13-F13 -> 1539.4563 | H13: =AVERAGE(D13,G13)*(Assumptions!$B$11*(1-Assumptions!$B$13)+(Assumptions!$B$12/12)*Assumptions!$B$13) -> 5416.8508 | I13: =H13*Assumptions!$B$22 -> 812.52762 | J13: =H13-I13 -> 4604.3232 | K13: =C13*Assumptions!$B$16+B13*Assumptions!$B$17 -> 2564.0606 | L13: =Assumptions!$B$18+C13*Assumptions!$B$19 -> 58.88654 | M13: =K13+L13 -> 2622.9471 | N13: =J13-M13 -> 1981.376 | O13: =Assumptions!$B$26+Assumptions!$B$28+Assumptions!$B$29+Assumptions!$B$30 -> 58.25 | P13: =N13-O13 -> 1923.126 | Q13: =MAX(0,P13)*Assumptions!$B$23 -> 346.16269 | R13: =P13-Q13 -> 1576.9634 | S13: =S12+R13 -> 5844.5443
A14: 12 | B14: =B13*(1+Assumptions!$B$6) -> 1739.275 | C14: =B14+D14 -> 3278.7313 | D14: =G13 -> 1539.4563 | E14: =B14*Assumptions!$B$7 -> 347.855 | F14: =D14*Assumptions!$B$8 -> 123.1565 | G14: =D14+E14-F14 -> 1764.1548 | H14: =AVERAGE(D14,G14)*(Assumptions!$B$11*(1-Assumptions!$B$13)+(Assumptions!$B$12/12)*Assumptions!$B$13) -> 6224.0033 | I14: =H14*Assumptions!$B$22 -> 933.6005 | J14: =H14-I14 -> 5290.4028 | K14: =C14*Assumptions!$B$16+B14*Assumptions!$B$17 -> 2908.6709 | L14: =Assumptions!$B$18+C14*Assumptions!$B$19 -> 62.787313 | M14: =K14+L14 -> 2971.4582 | N14: =J14-M14 -> 2318.9447 | O14: =Assumptions!$B$26+Assumptions!$B$28+Assumptions!$B$29+Assumptions!$B$30 -> 58.25 | P14: =N14-O14 -> 2260.6947 | Q14: =MAX(0,P14)*Assumptions!$B$23 -> 406.92504 | R14: =P14-Q14 -> 1853.7696 | S14: =S13+R14 -> 7698.3139
A16: YEAR 1 TOTAL | B16: =SUM(B3:B14) -> 12066.567 | H16: =SUM(H3:H14) -> 33899.034 | I16: =SUM(I3:I14) -> 5084.8551 | J16: =SUM(J3:J14) -> 28814.179 | K16: =SUM(K3:K14) -> 17998.551 | L16: =SUM(L3:L14) -> 561.81048 | M16: =SUM(M3:M14) -> 18560.361 | N16: =SUM(N3:N14) -> 10253.818 | O16: =SUM(O3:O14) -> 724 | ... R16: =SUM(R3:R14) -> 7698.3139 | S16: =S14 -> 7698.3139

Sheet Summary
A1: V-Tempe — Year 1 Summary
A3: REVENUE & GROWTH
A4: Total new installs (Year 1) | B4: ='Monthly Model'!B16 -> 12066.567
A5: Paying subscribers (Month 12, ending) | B5: ='Monthly Model'!G14 -> 1764.1548
A6: Exit MRR (Month 12 gross revenue) | B6: ='Monthly Model'!H14 -> 6224.0033
A7: Exit ARR (annualized) | B7: ='Monthly Model'!H14*12 -> 74688.04
A8: Year 1 gross revenue | B8: ='Monthly Model'!H16 -> 33899.034
A10: COSTS
A11: Year 1 total COGS (LLM + server) | B11: ='Monthly Model'!M16 -> 18560.361
A12: Year 1 total OpEx | B12: ='Monthly Model'!O16 -> 724
A13: Year 1 total store commission | B13: ='Monthly Model'!I16 -> 5084.8551
A14: Year 1 total tax | B14: ='Monthly Model'!Q16 -> 1831.504
A16: PROFITABILITY
A17: Year 1 net profit / (loss) | B17: ='Monthly Model'!S14 -> 7698.3139
A18: Net margin (Year 1 net profit / gross revenue) | B18: ='Monthly Model'!S14/'Monthly Model'!H16 -> 0.22709538
A19: First month cumulative profit turns positive | B19: =IFERROR(INDEX('Monthly Model'!A3:A14,MATCH(TRUE(),INDEX('Monthly Model'!S3:S14>0,0),0)),"not within 12 months") -> 6 | C19: Break-even month (first month where cumulative net profit > 0)
A21: Note: this model assumes no paid user acquisition beyond the marketing-spend line in Assumptions.
A22: If churn/conversion turn out worse than assumed, re-run with more conservative inputs on the Assumptions tab.
