Workbook

Sheet Assumptions
A1: V-Tempe — Financial Model Assumptions
A2: Edit blue cells (yellow fill) to change the scenario. All other sheets recalculate automatically.
A4: GROWTH & CONVERSION
A5: Month 1 new installs | B5: 500 | C5: Starting monthly new-install volume (organic/ASO, no paid marketing assumed)
A6: Month-over-month install growth | B6: 0.12 | C6: Organic growth rate of new installs, compounding monthly
A7: Trial-to-paid conversion rate | B7: 0.2 | C7: Share of new installs that convert to a paid subscription (assumes free trial, no perma-free tier)
A8: Monthly churn (paying subscribers) | B8: 0.08 | C8: Typical range for consumer mobile subscriptions is 5-10%/month
A10: PRICING
A11: Monthly plan price | B11: 3.99 | C11: Price shown to user, before store commission
A12: Annual plan price | B12: 39 | C12: Equivalent to $3.25/mo if paid annually
A13: Share of subscribers on annual plan | B13: 0.3 | C13: Rest are on the monthly plan
A15: COST OF SERVICE (COGS)
A16: LLM cost per active user / month | B16: 0.85 | C16: OpenRouter (Gemini 2.5 Flash) cost for weekly plan regen + chat; includes buffer for retry waste until backlog item #22 is fixed
A17: One-time LLM cost per new install (onboarding) | B17: 0.07 | C17: First bootstrap generation (training+nutrition+sleep), decomposed calls incl. retries
A18: Server fixed cost / month | B18: 30 | C18: Cloud Run baseline beyond GCP free tier, Secret Manager, logging
A19: Server variable cost / active user / month | B19: 0.01 | C19: Buffer for scale beyond Cloud Run free tier (2M req, 360k GiB-s/mo free)
A21: STORE & TAX
A22: App store commission | B22: 0.15 | C22: 15% under Apple Small Business Program / Google Play first $1M-per-year tier; use 30% for the standard-tier scenario
A23: Corporate tax rate (Armenia) | B23: 0.18 | C23: Standard AM profit tax ~18%. If IT-certification is obtained, this can drop toward 0% — verify current thresholds with a local accountant before relying on this.
A25: FIXED OPERATING EXPENSES (non-COGS)
A26: Apple Developer Program (annual, amortized) | B26: 8.25 | C26: $99/year ÷ 12
A27: Google Play (one-time, month 1 only) | B27: 25 | C27: One-time registration fee
A28: Tools & misc / month | B28: 50 | C28: Domain, monitoring, misc SaaS — placeholder, adjust to your actual stack
A29: Founder salary / month | B29: 0 | C29: 0 = pre-revenue solo founder draws nothing; set your real number once you want to pay yourself
A30: Marketing spend / month | B30: 0 | C30: 0 = organic growth only; set a budget to model paid acquisition (also raises Month-1 installs / growth rate above if used)
A32: Legend: yellow fill = edit these; black = formulas; green = link to another sheet.

Sheet Monthly Summary
A1: V-Tempe — Projected Audience & Profit by Month
A2: All figures link live to the Monthly Model tab — change any assumption and this table updates.
A3: Green cumulative-profit cell = break-even reached; red = still recovering Month-1 losses.
A4: Month | B4: New Installs | C4: Total Active Users | D4: Paying Subscribers | E4: Net Profit / (Loss) | F4: Cumulative Profit / (Loss)
A5: ='Monthly Model'!A3 | B5: ='Monthly Model'!B3 | C5: ='Monthly Model'!C3 | D5: ='Monthly Model'!G3 | E5: ='Monthly Model'!R3 | F5: ='Monthly Model'!S3
A6: ='Monthly Model'!A4 | B6: ='Monthly Model'!B4 | C6: ='Monthly Model'!C4 | D6: ='Monthly Model'!G4 | E6: ='Monthly Model'!R4 | F6: ='Monthly Model'!S4
A7: ='Monthly Model'!A5 | B7: ='Monthly Model'!B5 | C7: ='Monthly Model'!C5 | D7: ='Monthly Model'!G5 | E7: ='Monthly Model'!R5 | F7: ='Monthly Model'!S5
A8: ='Monthly Model'!A6 | B8: ='Monthly Model'!B6 | C8: ='Monthly Model'!C6 | D8: ='Monthly Model'!G6 | E8: ='Monthly Model'!R6 | F8: ='Monthly Model'!S6
A9: ='Monthly Model'!A7 | B9: ='Monthly Model'!B7 | C9: ='Monthly Model'!C7 | D9: ='Monthly Model'!G7 | E9: ='Monthly Model'!R7 | F9: ='Monthly Model'!S7
A10: ='Monthly Model'!A8 | B10: ='Monthly Model'!B8 | C10: ='Monthly Model'!C8 | D10: ='Monthly Model'!G8 | E10: ='Monthly Model'!R8 | F10: ='Monthly Model'!S8
A11: ='Monthly Model'!A9 | B11: ='Monthly Model'!B9 | C11: ='Monthly Model'!C9 | D11: ='Monthly Model'!G9 | E11: ='Monthly Model'!R9 | F11: ='Monthly Model'!S9
A12: ='Monthly Model'!A10 | B12: ='Monthly Model'!B10 | C12: ='Monthly Model'!C10 | D12: ='Monthly Model'!G10 | E12: ='Monthly Model'!R10 | F12: ='Monthly Model'!S10
A13: ='Monthly Model'!A11 | B13: ='Monthly Model'!B11 | C13: ='Monthly Model'!C11 | D13: ='Monthly Model'!G11 | E13: ='Monthly Model'!R11 | F13: ='Monthly Model'!S11
A14: ='Monthly Model'!A12 | B14: ='Monthly Model'!B12 | C14: ='Monthly Model'!C12 | D14: ='Monthly Model'!G12 | E14: ='Monthly Model'!R12 | F14: ='Monthly Model'!S12
A15: ='Monthly Model'!A13 | B15: ='Monthly Model'!B13 | C15: ='Monthly Model'!C13 | D15: ='Monthly Model'!G13 | E15: ='Monthly Model'!R13 | F15: ='Monthly Model'!S13
A16: ='Monthly Model'!A14 | B16: ='Monthly Model'!B14 | C16: ='Monthly Model'!C14 | D16: ='Monthly Model'!G14 | E16: ='Monthly Model'!R14 | F16: ='Monthly Model'!S14
A18: YEAR 1 | B18: =SUM(B5:B16) | E18: =SUM(E5:E16) | F18: =F16

Sheet Monthly Model
A1: V-Tempe — 12-Month Financial Model
A2: Month | B2: New Installs | C2: Active Users (cost base) | D2: Paying Subs (begin) | E2: New Conversions | F2: Churned Subs | G2: Paying Subs (end) | H2: Gross Revenue | I2: Store Commission | J2: Net Revenue | K2: LLM Cost | L2: Server Cost | M2: Total COGS | N2: Gross Profit | O2: OpEx | P2: Pretax Profit | Q2: Tax | R2: Net Profit | S2: Cumulative Net Profit
A3: 1 | B3: =Assumptions!$B$5 | C3: =B3+D3 | D3: 0 | E3: =B3*Assumptions!$B$7 | F3: =D3*Assumptions!$B$8 | G3: =D3+E3-F3 | H3: =AVERAGE(D3,G3)*(Assumptions!$B$11*(1-Assumptions!$B$13)+(Assumptions!$B$12/12)*Assumptions!$B$13) | I3: =H3*Assumptions!$B$22 | J3: =H3-I3 | K3: =C3*Assumptions!$B$16+B3*Assumptions!$B$17 | L3: =Assumptions!$B$18+C3*Assumptions!$B$19 | M3: =K3+L3 | N3: =J3-M3 | O3: =Assumptions!$B$26+Assumptions!$B$28+Assumptions!$B$29+Assumptions!$B$30+Assumptions!$B$27 | P3: =N3-O3 | Q3: =MAX(0,P3)*Assumptions!$B$23 | R3: =P3-Q3 | S3: =R3
A4: 2 | B4: =B3*(1+Assumptions!$B$6) | C4: =B4+D4 | D4: =G3 | E4: =B4*Assumptions!$B$7 | F4: =D4*Assumptions!$B$8 | G4: =D4+E4-F4 | H4: =AVERAGE(D4,G4)*(Assumptions!$B$11*(1-Assumptions!$B$13)+(Assumptions!$B$12/12)*Assumptions!$B$13) | I4: =H4*Assumptions!$B$22 | J4: =H4-I4 | K4: =C4*Assumptions!$B$16+B4*Assumptions!$B$17 | L4: =Assumptions!$B$18+C4*Assumptions!$B$19 | M4: =K4+L4 | N4: =J4-M4 | O4: =Assumptions!$B$26+Assumptions!$B$28+Assumptions!$B$29+Assumptions!$B$30 | P4: =N4-O4 | Q4: =MAX(0,P4)*Assumptions!$B$23 | R4: =P4-Q4 | S4: =S3+R4
A5: 3 | B5: =B4*(1+Assumptions!$B$6) | C5: =B5+D5 | D5: =G4 | E5: =B5*Assumptions!$B$7 | F5: =D5*Assumptions!$B$8 | G5: =D5+E5-F5 | H5: =AVERAGE(D5,G5)*(Assumptions!$B$11*(1-Assumptions!$B$13)+(Assumptions!$B$12/12)*Assumptions!$B$13) | I5: =H5*Assumptions!$B$22 | J5: =H5-I5 | K5: =C5*Assumptions!$B$16+B5*Assumptions!$B$17 | L5: =Assumptions!$B$18+C5*Assumptions!$B$19 | M5: =K5+L5 | N5: =J5-M5 | O5: =Assumptions!$B$26+Assumptions!$B$28+Assumptions!$B$29+Assumptions!$B$30 | P5: =N5-O5 | Q5: =MAX(0,P5)*Assumptions!$B$23 | R5: =P5-Q5 | S5: =S4+R5
A6: 4 | B6: =B5*(1+Assumptions!$B$6) | C6: =B6+D6 | D6: =G5 | E6: =B6*Assumptions!$B$7 | F6: =D6*Assumptions!$B$8 | G6: =D6+E6-F6 | H6: =AVERAGE(D6,G6)*(Assumptions!$B$11*(1-Assumptions!$B$13)+(Assumptions!$B$12/12)*Assumptions!$B$13) | I6: =H6*Assumptions!$B$22 | J6: =H6-I6 | K6: =C6*Assumptions!$B$16+B6*Assumptions!$B$17 | L6: =Assumptions!$B$18+C6*Assumptions!$B$19 | M6: =K6+L6 | N6: =J6-M6 | O6: =Assumptions!$B$26+Assumptions!$B$28+Assumptions!$B$29+Assumptions!$B$30 | P6: =N6-O6 | Q6: =MAX(0,P6)*Assumptions!$B$23 | R6: =P6-Q6 | S6: =S5+R6
A7: 5 | B7: =B6*(1+Assumptions!$B$6) | C7: =B7+D7 | D7: =G6 | E7: =B7*Assumptions!$B$7 | F7: =D7*Assumptions!$B$8 | G7: =D7+E7-F7 | H7: =AVERAGE(D7,G7)*(Assumptions!$B$11*(1-Assumptions!$B$13)+(Assumptions!$B$12/12)*Assumptions!$B$13) | I7: =H7*Assumptions!$B$22 | J7: =H7-I7 | K7: =C7*Assumptions!$B$16+B7*Assumptions!$B$17 | L7: =Assumptions!$B$18+C7*Assumptions!$B$19 | M7: =K7+L7 | N7: =J7-M7 | O7: =Assumptions!$B$26+Assumptions!$B$28+Assumptions!$B$29+Assumptions!$B$30 | P7: =N7-O7 | Q7: =MAX(0,P7)*Assumptions!$B$23 | R7: =P7-Q7 | S7: =S6+R7
A8: 6 | B8: =B7*(1+Assumptions!$B$6) | C8: =B8+D8 | D8: =G7 | E8: =B8*Assumptions!$B$7 | F8: =D8*Assumptions!$B$8 | G8: =D8+E8-F8 | H8: =AVERAGE(D8,G8)*(Assumptions!$B$11*(1-Assumptions!$B$13)+(Assumptions!$B$12/12)*Assumptions!$B$13) | I8: =H8*Assumptions!$B$22 | J8: =H8-I8 | K8: =C8*Assumptions!$B$16+B8*Assumptions!$B$17 | L8: =Assumptions!$B$18+C8*Assumptions!$B$19 | M8: =K8+L8 | N8: =J8-M8 | O8: =Assumptions!$B$26+Assumptions!$B$28+Assumptions!$B$29+Assumptions!$B$30 | P8: =N8-O8 | Q8: =MAX(0,P8)*Assumptions!$B$23 | R8: =P8-Q8 | S8: =S7+R8
A9: 7 | B9: =B8*(1+Assumptions!$B$6) | C9: =B9+D9 | D9: =G8 | E9: =B9*Assumptions!$B$7 | F9: =D9*Assumptions!$B$8 | G9: =D9+E9-F9 | H9: =AVERAGE(D9,G9)*(Assumptions!$B$11*(1-Assumptions!$B$13)+(Assumptions!$B$12/12)*Assumptions!$B$13) | I9: =H9*Assumptions!$B$22 | J9: =H9-I9 | K9: =C9*Assumptions!$B$16+B9*Assumptions!$B$17 | L9: =Assumptions!$B$18+C9*Assumptions!$B$19 | M9: =K9+L9 | N9: =J9-M9 | O9: =Assumptions!$B$26+Assumptions!$B$28+Assumptions!$B$29+Assumptions!$B$30 | P9: =N9-O9 | Q9: =MAX(0,P9)*Assumptions!$B$23 | R9: =P9-Q9 | S9: =S8+R9
A10: 8 | B10: =B9*(1+Assumptions!$B$6) | C10: =B10+D10 | D10: =G9 | E10: =B10*Assumptions!$B$7 | F10: =D10*Assumptions!$B$8 | G10: =D10+E10-F10 | H10: =AVERAGE(D10,G10)*(Assumptions!$B$11*(1-Assumptions!$B$13)+(Assumptions!$B$12/12)*Assumptions!$B$13) | I10: =H10*Assumptions!$B$22 | J10: =H10-I10 | K10: =C10*Assumptions!$B$16+B10*Assumptions!$B$17 | L10: =Assumptions!$B$18+C10*Assumptions!$B$19 | M10: =K10+L10 | N10: =J10-M10 | O10: =Assumptions!$B$26+Assumptions!$B$28+Assumptions!$B$29+Assumptions!$B$30 | P10: =N10-O10 | Q10: =MAX(0,P10)*Assumptions!$B$23 | R10: =P10-Q10 | S10: =S9+R10
A11: 9 | B11: =B10*(1+Assumptions!$B$6) | C11: =B11+D11 | D11: =G10 | E11: =B11*Assumptions!$B$7 | F11: =D11*Assumptions!$B$8 | G11: =D11+E11-F11 | H11: =AVERAGE(D11,G11)*(Assumptions!$B$11*(1-Assumptions!$B$13)+(Assumptions!$B$12/12)*Assumptions!$B$13) | I11: =H11*Assumptions!$B$22 | J11: =H11-I11 | K11: =C11*Assumptions!$B$16+B11*Assumptions!$B$17 | L11: =Assumptions!$B$18+C11*Assumptions!$B$19 | M11: =K11+L11 | N11: =J11-M11 | O11: =Assumptions!$B$26+Assumptions!$B$28+Assumptions!$B$29+Assumptions!$B$30 | P11: =N11-O11 | Q11: =MAX(0,P11)*Assumptions!$B$23 | R11: =P11-Q11 | S11: =S10+R11
A12: 10 | B12: =B11*(1+Assumptions!$B$6) | C12: =B12+D12 | D12: =G11 | E12: =B12*Assumptions!$B$7 | F12: =D12*Assumptions!$B$8 | G12: =D12+E12-F12 | H12: =AVERAGE(D12,G12)*(Assumptions!$B$11*(1-Assumptions!$B$13)+(Assumptions!$B$12/12)*Assumptions!$B$13) | I12: =H12*Assumptions!$B$22 | J12: =H12-I12 | K12: =C12*Assumptions!$B$16+B12*Assumptions!$B$17 | L12: =Assumptions!$B$18+C12*Assumptions!$B$19 | M12: =K12+L12 | N12: =J12-M12 | O12: =Assumptions!$B$26+Assumptions!$B$28+Assumptions!$B$29+Assumptions!$B$30 | P12: =N12-O12 | Q12: =MAX(0,P12)*Assumptions!$B$23 | R12: =P12-Q12 | S12: =S11+R12
A13: 11 | B13: =B12*(1+Assumptions!$B$6) | C13: =B13+D13 | D13: =G12 | E13: =B13*Assumptions!$B$7 | F13: =D13*Assumptions!$B$8 | G13: =D13+E13-F13 | H13: =AVERAGE(D13,G13)*(Assumptions!$B$11*(1-Assumptions!$B$13)+(Assumptions!$B$12/12)*Assumptions!$B$13) | I13: =H13*Assumptions!$B$22 | J13: =H13-I13 | K13: =C13*Assumptions!$B$16+B13*Assumptions!$B$17 | L13: =Assumptions!$B$18+C13*Assumptions!$B$19 | M13: =K13+L13 | N13: =J13-M13 | O13: =Assumptions!$B$26+Assumptions!$B$28+Assumptions!$B$29+Assumptions!$B$30 | P13: =N13-O13 | Q13: =MAX(0,P13)*Assumptions!$B$23 | R13: =P13-Q13 | S13: =S12+R13
A14: 12 | B14: =B13*(1+Assumptions!$B$6) | C14: =B14+D14 | D14: =G13 | E14: =B14*Assumptions!$B$7 | F14: =D14*Assumptions!$B$8 | G14: =D14+E14-F14 | H14: =AVERAGE(D14,G14)*(Assumptions!$B$11*(1-Assumptions!$B$13)+(Assumptions!$B$12/12)*Assumptions!$B$13) | I14: =H14*Assumptions!$B$22 | J14: =H14-I14 | K14: =C14*Assumptions!$B$16+B14*Assumptions!$B$17 | L14: =Assumptions!$B$18+C14*Assumptions!$B$19 | M14: =K14+L14 | N14: =J14-M14 | O14: =Assumptions!$B$26+Assumptions!$B$28+Assumptions!$B$29+Assumptions!$B$30 | P14: =N14-O14 | Q14: =MAX(0,P14)*Assumptions!$B$23 | R14: =P14-Q14 | S14: =S13+R14
A16: YEAR 1 TOTAL | B16: =SUM(B3:B14) | H16: =SUM(H3:H14) | I16: =SUM(I3:I14) | J16: =SUM(J3:J14) | K16: =SUM(K3:K14) | L16: =SUM(L3:L14) | M16: =SUM(M3:M14) | N16: =SUM(N3:N14) | O16: =SUM(O3:O14) | ... R16: =SUM(R3:R14) | S16: =S14

Sheet Summary
A1: V-Tempe — Year 1 Summary
A3: REVENUE & GROWTH
A4: Total new installs (Year 1) | B4: ='Monthly Model'!B16
A5: Paying subscribers (Month 12, ending) | B5: ='Monthly Model'!G14
A6: Exit MRR (Month 12 gross revenue) | B6: ='Monthly Model'!H14
A7: Exit ARR (annualized) | B7: ='Monthly Model'!H14*12
A8: Year 1 gross revenue | B8: ='Monthly Model'!H16
A10: COSTS
A11: Year 1 total COGS (LLM + server) | B11: ='Monthly Model'!M16
A12: Year 1 total OpEx | B12: ='Monthly Model'!O16
A13: Year 1 total store commission | B13: ='Monthly Model'!I16
A14: Year 1 total tax | B14: ='Monthly Model'!Q16
A16: PROFITABILITY
A17: Year 1 net profit / (loss) | B17: ='Monthly Model'!S14
A18: Net margin (Year 1 net profit / gross revenue) | B18: ='Monthly Model'!S14/'Monthly Model'!H16
A19: First month cumulative profit turns positive | B19: =IFERROR(INDEX('Monthly Model'!A3:A14,MATCH(TRUE,INDEX('Monthly Model'!S3:S14>0,0),0)),"not within 12 months") | C19: Break-even month (first month where cumulative net profit > 0)
A21: Note: this model assumes no paid user acquisition beyond the marketing-spend line in Assumptions.
A22: If churn/conversion turn out worse than assumed, re-run with more conservative inputs on the Assumptions tab.
